{
    "team": [
        {
            "name": "Dissanayaka M.A.S.R",
            "email": "e19087@eng.pdn.ac.lk",
            "eNumber": "E/19/087"
        },
        {
            "name": "Neranji W.K.G.A.G",
            "email": "e19260@eng.pdn.ac.lk",
            "eNumber": "E/19/260"
        },
        {
            "name": "Weerasingha W.A.C.J",
            "email": "e19423@eng.pdn.ac.lk",
            "eNumber": "E/19/423"
        },
        {
            "name": "Ekanayake E.M.M.U.B",
            "email": "e17083@eng.pdn.ac.lk",
            "eNumber": "E/17/083"
        },
        {
            "name": "Weerasinghe H.A.S.N",
            "email": "e19424@eng.pdn.ac.lk",
            "eNumber": "E/19/424"
        }
    ],
    "supervisors": [
        {
            "name": "Dr. Supervisor 1",
            "email": "email@eng.pdn.ac.lk"
        },
        {
            "name": "Supervisor 2",
            "email": "email@eng.pdn.ac.lk"
        }
    ],
    "tags": ["Web", "Embedded Systems"]
}
